pyecg/__init__.py
pyecg/dataset.py
pyecg/ecg.py
pyecg/sequence_data.py
pyecg/subject_info.py
pyecg/annotations/README.rst
pyecg/annotations/__init__.py
pyecg/annotations/annotations.py
pyecg/annotations/constants.py
pyecg/importers/__init__.py
pyecg/importers/importer.py
pyecg/importers/ishine.py
pyecg/importers/wfdb.py
pyECG-0.0.9.1.dist-info/AUTHORS.rst
pyECG-0.0.9.1.dist-info/LICENSE.txt
pyECG-0.0.9.1.dist-info/METADATA
pyECG-0.0.9.1.dist-info/WHEEL
pyECG-0.0.9.1.dist-info/top_level.txt
pyECG-0.0.9.1.dist-info/RECORD
