Metadata-Version: 2.1
Name: pyECG
Version: 0.0.9.1
Summary: Python ECG toolkit for common ECG dataset format I/O
Home-page: https://github.com/taoyilee/pyECG
Author: TAOYILEE
Author-email: taoyil@uci.edu
License: mit
Platform: any
Classifier: Development Status :: 4 - Beta
Classifier: Programming Language :: Python :: 3.6
Classifier: Environment :: Console
Classifier: Programming Language :: Python
Requires-Dist: ishneholterlib (==2017.4.11)
Requires-Dist: numpy
Requires-Dist: wfdb (==2.2.1)
Requires-Dist: pytest
Requires-Dist: pytest-cov
Provides-Extra: testing
Requires-Dist: pytest ; extra == 'testing'
Requires-Dist: pytest-cov ; extra == 'testing'
